LICENSE
MANIFEST.in
README.md
requirements.txt
setup.cfg
setup.py
./setup.py
./jasmine/__init__.py
./jasmine/ci.py
./jasmine/config.py
./jasmine/console_formatter.py
./jasmine/entry_points.py
./jasmine/js_api_parser.py
./jasmine/result.py
./jasmine/result_list.py
./jasmine/standalone.py
./jasmine/url_builder.py
./jasmine/utils.py
./jasmine/templates/__init__.py
./test/__init__.py
./test/ci_test.py
./test/config_test.py
./test/console_formatter_test.py
./test/entry_points_test.py
./test/integration_test.py
./test/jasmine_core_test.py
./test/js_api_parser_test.py
./test/result_list_test.py
./test/result_test.py
./test/url_builder_test.py
./test/helpers/__init__.py
./test/helpers/fake_config.py
jasmine/__init__.py
jasmine/ci.py
jasmine/config.py
jasmine/console_formatter.py
jasmine/entry_points.py
jasmine/js_api_parser.py
jasmine/result.py
jasmine/result_list.py
jasmine/standalone.py
jasmine/url_builder.py
jasmine/utils.py
jasmine.egg-info/PKG-INFO
jasmine.egg-info/SOURCES.txt
jasmine.egg-info/dependency_links.txt
jasmine.egg-info/entry_points.txt
jasmine.egg-info/requires.txt
jasmine.egg-info/top_level.txt
jasmine/templates/__init__.py
jasmine/templates/runner.html
test/helpers/__init__.py
test/helpers/fake_config.py